medmij_oauth/__init__.py
medmij_oauth/client/__init__.py
medmij_oauth/client/client.py
medmij_oauth/client/data_store.py
medmij_oauth/client/gnl.py
medmij_oauth/client/validation.py
medmij_oauth/client/data_store_implementations/__init__.py
medmij_oauth/client/data_store_implementations/in_memory.py
medmij_oauth/exceptions/__init__.py
medmij_oauth/exceptions/exceptions.py
medmij_oauth/server/__init__.py
medmij_oauth/server/data_store.py
medmij_oauth/server/med_mij_uuid.py
medmij_oauth/server/server.py
medmij_oauth/server/tokens.py
medmij_oauth/server/validation.py
medmij_oauth/server/data_store_implementations/__init__.py
medmij_oauth/server/data_store_implementations/in_memory.py
medmij_oauth-0.1.0.dist-info/LICENSE
medmij_oauth-0.1.0.dist-info/METADATA
medmij_oauth-0.1.0.dist-info/WHEEL
medmij_oauth-0.1.0.dist-info/top_level.txt
medmij_oauth-0.1.0.dist-info/RECORD
