Metadata-Version: 2.1
Name: medmij-oauth
Version: 0.1.0
Summary: Libraries for oauth client/server implementations according to the MedMij requirements
Home-page: https://github.com/GidsOpenStandaarden/OpenPGO-Medmij-ImplementatieBouwstenen-Python-OAuth
Author: Bas Kloosterman
Author-email: bask@whiteboxsystems.nl
License: AGPLv3
Platform: UNKNOWN
Classifier: Programming Language :: Python :: 3.7
Classifier: Intended Audience :: Healthcare Industry
Requires-Python: >=3.6
Requires-Dist: sphinxcontrib-asyncio
Requires-Dist: medmij-lists
